[
  {
    "Name": "Yozio",
    "Value": 59.56
  },
  {
    "Name": "Quire",
    "Value": 451.15999999999997
  },
  {
    "Name": "Fliptune",
    "Value": 637.0
  },
  {
    "Name": "Babbleset",
    "Value": 711.5
  },
  {
    "Name": "Oyondu",
    "Value": 1147.69
  },
  {
    "Name": "Fivebridge",
    "Value": 1194.77
  },
  {
    "Name": "Gabspot",
    "Value": 1564.62
  },
  {
    "Name": "Bubbletube",
    "Value": 1607.0
  },
  {
    "Name": "Wikizz",
    "Value": 1759.9
  },
  {
    "Name": "Chatterpoint",
    "Value": 1901.5800000000002
  },
  {
    "Name": "InnoZ",
    "Value": 1933.71
  },
  {
    "Name": "Devbug",
    "Value": 2530.07
  },
  {
    "Name": "Innotype",
    "Value": 2611.49
  },
  {
    "Name": "Skyvu",
    "Value": 3260.0
  },
  {
    "Name": "Linklinks",
    "Value": 3299.9500000000003
  },
  {
    "Name": "Geba",
    "Value": 3716.64
  },
  {
    "Name": "Edgeclub",
    "Value": 5766.16
  },
  {
    "Name": "Demimbu",
    "Value": 6407.929999999999
  },
  {
    "Name": "Warehouse",
    "Value": 8790.529999999999
  },
  {
    "Name": "Topiclounge",
    "Value": 11158.31
  }
]